agora/__init__.py
agora/client.py
agora/metadata.json
agora/collector/__init__.py
agora/collector/cache.py
agora/collector/execution.py
agora/collector/http.py
agora/collector/plan.py
agora/collector/remote.py
agora/collector/scholar.py
agora/collector/wrapper.py
agora/engine/__init__.py
agora/engine/fountain/__init__.py
agora/engine/fountain/index.py
agora/engine/fountain/onto.py
agora/engine/fountain/path.py
agora/engine/fountain/schema.py
agora/engine/fountain/seed.py
agora/engine/plan/__init__.py
agora/engine/plan/agp.py
agora/engine/plan/graph.py
agora/engine/utils/__init__.py
agora/engine/utils/cache.py
agora/engine/utils/graph.py
agora/engine/utils/kv.py
agora/engine/utils/lists.py
agora/graph/__init__.py
agora/graph/evaluate.py
agora/graph/incremental.py
agora/graph/processor.py
agora/server/__init__.py
agora/server/fountain.py
agora/server/fragment.py
agora/server/planner.py
agora/server/publish.py
agora/server/sparql.py
agora/server/static/Monoxil.otf
agora/server/static/agora-im.png
agora/server/static/agora.png
agora/server/static/favicon.ico
agora/server/static/logoOEG.png
agora/server/static/main.js
agora/server/static/oboe-browser.js
agora/server/static/styles.css
agora/server/static/upm.png
agora/server/templates/base.html
agora/server/templates/sparql.html
agora/tests/__init__.py
agora/tests/ted/__init__.py
agora/tests/ted/gw_test.py
agora/tests/ted/parse_test.py
agora_py-0.5.47.dist-info/LICENSE
agora_py-0.5.47.dist-info/METADATA
agora_py-0.5.47.dist-info/WHEEL
agora_py-0.5.47.dist-info/top_level.txt
agora_py-0.5.47.dist-info/RECORD
